eskriper/__init__.py
eskriper/selenium_driver.py
tests/__init__.py
tests/test_allow_javascript.py
eskriper-0.2.2.dist-info/LICENSE
eskriper-0.2.2.dist-info/METADATA
eskriper-0.2.2.dist-info/WHEEL
eskriper-0.2.2.dist-info/top_level.txt
eskriper-0.2.2.dist-info/RECORD
