Metadata-Version: 2.1
Name: eskriper
Version: 0.2.2
Summary: Python helper utilities
Author: Kristian Marlowe Ole
Author-email: krismar.ole@gmail.com
License: GPLv3+
Requires-Python: >=3.8
License-File: LICENSE
